bindu/__init__.py
bindu/__version__.py
bindu/_version.py
bindu/settings.py
bindu/common/__init__.py
bindu/common/models.py
bindu/common/protocol/__init__.py
bindu/common/protocol/types.py
bindu/extensions/__init__.py
bindu/extensions/did/__init__.py
bindu/extensions/did/did_agent_extension.py
bindu/extensions/did/validation.py
bindu/extensions/x402/__init__.py
bindu/extensions/x402/constants.py
bindu/extensions/x402/extension.py
bindu/extensions/x402/utils.py
bindu/extensions/x402/x402_agent_extension.py
bindu/observability/__init__.py
bindu/observability/openinference.py
bindu/observability/sentry.py
bindu/penguin/__init__.py
bindu/penguin/bindufy.py
bindu/penguin/config_validator.py
bindu/penguin/did_setup.py
bindu/penguin/manifest.py
bindu/server/__init__.py
bindu/server/applications.py
bindu/server/metrics.py
bindu/server/task_manager.py
bindu/server/endpoints/__init__.py
bindu/server/endpoints/a2a_protocol.py
bindu/server/endpoints/agent_card.py
bindu/server/endpoints/did_endpoints.py
bindu/server/endpoints/health.py
bindu/server/endpoints/metrics.py
bindu/server/endpoints/negotiation.py
bindu/server/endpoints/payment_sessions.py
bindu/server/endpoints/skills.py
bindu/server/handlers/__init__.py
bindu/server/handlers/context_handlers.py
bindu/server/handlers/message_handlers.py
bindu/server/handlers/task_handlers.py
bindu/server/middleware/__init__.py
bindu/server/middleware/metrics.py
bindu/server/middleware/auth/__init__.py
bindu/server/middleware/auth/auth0.py
bindu/server/middleware/auth/base.py
bindu/server/middleware/auth/cognito.py
bindu/server/middleware/x402/__init__.py
bindu/server/middleware/x402/payment_session_manager.py
bindu/server/middleware/x402/x402_middleware.py
bindu/server/negotiation/__init__.py
bindu/server/negotiation/capability_calculator.py
bindu/server/negotiation/embedder.py
bindu/server/notifications/__init__.py
bindu/server/notifications/push_manager.py
bindu/server/scheduler/__init__.py
bindu/server/scheduler/base.py
bindu-2026.3.5.dist-info/METADATA
bindu-2026.3.5.dist-info/WHEEL
bindu-2026.3.5.dist-info/RECORD
