Metadata-Version: 2.4
Name: bindu
Version: 2026.3.5
Summary: A protocol framework for agent-to-agent communication
Author-email: Raahul Dutta <raahul@getbindu.com>
License: Apache-2.0
Classifier: License :: OSI Approved :: Apache Software License
Classifier: Operating System :: OS Independent
Classifier: Programming Language :: Python :: 3
Requires-Python: >=3.12
Requires-Dist: agno>=2.3.8
Requires-Dist: aiofiles>=24.1.0
Requires-Dist: alembic>=1.13.0
Requires-Dist: asyncpg>=0.29.0
Requires-Dist: base58>=2.1.1
Requires-Dist: cdp-sdk>=0.21.0
Requires-Dist: coinbase-advanced-py>=1.8.2
Requires-Dist: cryptography>=44.0.2
Requires-Dist: ddgs>=9.9.3
Requires-Dist: detect-secrets>=1.5.0
Requires-Dist: eth-account>=0.13.7
Requires-Dist: httpx>=0.27.0
Requires-Dist: loguru>=0.7.3
Requires-Dist: numpy>=1.24.0
Requires-Dist: openai>=2.9.0
Requires-Dist: opentelemetry-api>=1.35.0
Requires-Dist: opentelemetry-exporter-otlp-proto-http>=1.35.0
Requires-Dist: opentelemetry-exporter-otlp>=1.35.0
Requires-Dist: opentelemetry-instrumentation-fastapi>=0.56b0
Requires-Dist: opentelemetry-instrumentation-httpx>=0.56b0
Requires-Dist: opentelemetry-sdk>=1.35.0
Requires-Dist: orjson>=3.10.18
Requires-Dist: pydantic>=1.8.2
Requires-Dist: pyjwt[crypto]>=2.8.0
Requires-Dist: pyperclip>=1.11.0
Requires-Dist: pyyaml>=6.0.2
Requires-Dist: redis>=7.1.0
Requires-Dist: requests>=2.31.0
Requires-Dist: rich>=13.0.0
Requires-Dist: sentry-sdk>=2.0.0
Requires-Dist: sqlalchemy[asyncio]>=2.0.0
Requires-Dist: starlette>=0.48.0
Requires-Dist: tenacity==8.5.0
Requires-Dist: ty>=0.0.1a14
Requires-Dist: uvicorn>=0.15.0
Requires-Dist: web3>=7.13.0
Requires-Dist: x402>=0.2.1
Provides-Extra: sec
Requires-Dist: detect-secrets>=1.5.0; extra == 'sec'
Provides-Extra: ui
Requires-Dist: httpx>=0.27.0; extra == 'ui'
